[ 
    {
      "id": 1,
      "nombre": "Iron Maiden",
      "descripcion":"Un concierto de leyenda, no te querras perder la que posiblemente sea la última gira de estas leyendas vivas de la música",
      "localidad":"Murcia",
      "poblacion":"Murcia",
      "fecha":"20/07/2023",
      "fotos":["IM1.jpg","IM2.jpg","IM3.jpg"],
      "estado":1,
      "url":"https://www.ticketmaster.es/artist/iron-maiden-entradas/1225",
      "lat":376097371,
      "lon":-0.9986284
    },
    {
      "id": 2,
      "nombre": "Rock Imperium",
      "descripcion":"Un macro festival en el que se dan cita parte de las más grandes bandas de rock de la historia",
      "localidad":"Catagena",
      "poblacion":"Cartagena",
      "fecha":"24/06/2023",
      "fotos":["RI1.jpg","RI2.jpg","RI3.jpg"],
      "estado":1,
      "url":"https://www.madnesslive.es/es/pagina/196-rock-imperium-festival-2024",
      "lat":376097371,
      "lon":-0.9986284
    },
    {
      "id": 3,
      "nombre": "Leyendas del rock",
      "descripcion":"Un macro festival en el que se dan cita parte de las más grandes bandas de rock de la historia",
      "localidad":"Villena",
      "poblacion":"Alicante",
      "fecha":"31/07/2023",
      "fotos":["RI1.jpg","RI2.jpg","RI3.jpg"],
      "estado":1,
      "url":"https://www.madnesslive.es/es/pagina/196-rock-imperium-festival-2024",
      "lat":376097371,
      "lon":-0.9986284
    }
]

